LICENSE
MANIFEST.in
README.rst
VERSION
requirements.txt
setup.py
unicore/__init__.py
unicore.content.egg-info/PKG-INFO
unicore.content.egg-info/SOURCES.txt
unicore.content.egg-info/dependency_links.txt
unicore.content.egg-info/namespace_packages.txt
unicore.content.egg-info/not-zip-safe
unicore.content.egg-info/requires.txt
unicore.content.egg-info/top_level.txt
unicore/content/__init__.py
unicore/content/models.py