Metadata-Version: 1.1
Name: unicore.content
Version: 1.0.2
Summary: Content models for Universal Core
Home-page: http://github.com/universalcore/unicore.content
Author: Praekelt Foundation
Author-email: dev@praekelt.com
License: BSD
Keywords: elastic-git,universal,core
Platform: UNKNOWN
Classifier: Programming Language :: Python
Classifier: Framework :: Pyramid
Classifier: Topic :: Internet :: WWW/HTTP
Classifier: Topic :: Internet :: WWW/HTTP :: WSGI :: Application
